SWC/__init__.py
SpiderWebCrawler-0.0.1.dist-info/LICENSE.txt
SpiderWebCrawler-0.0.1.dist-info/METADATA
SpiderWebCrawler-0.0.1.dist-info/WHEEL
SpiderWebCrawler-0.0.1.dist-info/top_level.txt
SpiderWebCrawler-0.0.1.dist-info/RECORD
